proforma/__init__.py
proforma/component.py
proforma/exceptions.py
proforma/aws/__init__.py
proforma/aws/acm.py
proforma/aws/apigateway.py
proforma/aws/batch.py
proforma/aws/iam.py
proforma/aws/llambda.py
proforma/aws/s3.py
proforma/aws/sns.py
proforma-0.2.1.dist-info/METADATA
proforma-0.2.1.dist-info/RECORD
proforma-0.2.1.dist-info/WHEEL
proforma-0.2.1.dist-info/top_level.txt
