Metadata-Version: 2.1
Name: proforma
Version: 0.2.1
Summary: Simple library for setting up AWS Infrastructure.
Home-page: http://github.com/HumanCellAtlas/proforma
Author: Sam Pierson
Author-email: spierson@chanzuckerberg.com
License: MIT
Platform: MacOS X
Platform: Posix
Classifier: Intended Audience :: Developers
Classifier: License :: OSI Approved :: MIT License
Classifier: Operating System :: MacOS :: MacOS X
Classifier: Operating System :: POSIX
Classifier: Programming Language :: Python :: 3.6
Requires-Dist: boto3
